examples
mnkytw
