Metadata-Version: 2.1
Name: monkeys-typewriter
Version: 1.0.4
Summary: Monkey's Typewriter PEG parser
Home-page: https://tryal.ai/
Author: Adam Green
Author-email: adam@tryal.ai
License: UNKNOWN
Keywords: PEG,parser,grammar
Platform: UNKNOWN
Classifier: Programming Language :: Python :: 3
Classifier: License :: OSI Approved :: Apache Software License
Classifier: Operating System :: OS Independent
Requires-Python: >=3.6
